PyLogical/__init__.py
PyLogical/attributes.py
PyLogical/modulo.py
pylogical220-0.1.0.dist-info/licenses/LICENSE
pylogical220-0.1.0.dist-info/METADATA
pylogical220-0.1.0.dist-info/WHEEL
pylogical220-0.1.0.dist-info/top_level.txt
pylogical220-0.1.0.dist-info/RECORD
