Metadata-Version: 2.4
Name: pylogical220
Version: 0.1.0
Summary: Useful package for logic of python, contains 18 attributes.
Home-page: https://github.com/Felipe057a/pip
Author: as-220
License: MIT License
Requires-Python: >=3.7
License-File: LICENSE
Dynamic: home-page
Dynamic: license-file
